northpole/__about__.py
northpole/__init__.py
northpole/parsers.py
northpole-0.6.dist-info/METADATA
northpole-0.6.dist-info/WHEEL
northpole-0.6.dist-info/licenses/LICENSE.txt
northpole-0.6.dist-info/RECORD
