Metadata-Version: 2.1
Name: northpole
Version: 0.6
Summary: A set of utilities useful for solving Advent of Code challenges
Project-URL: Documentation, https://northpole.readthedocs.io/en/latest/
Project-URL: Issues, https://github.com/stephenlutes/northpole/issues
Project-URL: Source, https://github.com/stephenlutes/northpole
Author: Stephen Lutes
License-Expression: MIT
License-File: LICENSE.txt
Classifier: Development Status :: 4 - Beta
Classifier: Programming Language :: Python
Classifier: Programming Language :: Python :: 3.8
Classifier: Programming Language :: Python :: 3.9
Classifier: Programming Language :: Python :: 3.10
Classifier: Programming Language :: Python :: 3.11
Classifier: Programming Language :: Python :: 3.12
Classifier: Programming Language :: Python :: Implementation :: CPython
Classifier: Programming Language :: Python :: Implementation :: PyPy
Requires-Python: >=3.8
